rstypes-0.1.1.dist-info/METADATA
rstypes-0.1.1.dist-info/WHEEL
rstypes-0.1.1.dist-info/licenses/LICENSE
rstypes/__init__.py
rstypes/_rstypes.cpython-312-darwin.so
rstypes/_rstypes.pyi
rstypes/py.typed
rstypes-0.1.1.dist-info/RECORD
