Metadata-Version: 2.4
Name: rstypes
Version: 0.1.1
Classifier: Programming Language :: Rust
Classifier: Programming Language :: Python :: Implementation :: CPython
Classifier: Programming Language :: Python :: Implementation :: PyPy
License-File: LICENSE
Summary: Thread-safe async-aware types for Python written in Rust
Author: Brian Goo
License-Expression: MIT
Requires-Python: >=3.10
Project-URL: Homepage, https://github.com/brian-goo/rstypes
Project-URL: Source, https://github.com/brian-goo/rstypes
